{
    "svm": {
        "tol": 0.001,
        "probability": true,
        "kernel": "rbf",
        "gamma": 0.1,
        "class_weight": "balanced",
        "C": 1e-05
    },
    "logistic_regression": {
        "tol": 0.1,
        "solver": "lbfgs",
        "random_state": 42,
        "max_iter": 2000,
        "class_weight": "balanced",
        "C": 0.1
    },
    "lstm": {
        "hidden_size": 9,
        "num_layers": 2,
        "dropout": 0.3611941770167,
        "learning_rate": 0.00020211751738079248,
        "batch_size": 8,
        "weight_decay": 0.025797232844293954
    },
    "transformer": {
        "d_model": 17,
        "num_layers": 1,
        "dropout": 0.6927226579863768,
        "learning_rate": 0.0001031314701764871,
        "batch_size": 8,
        "nhead": 2,
        "weight_decay": 0.00959027690353008
    }
}